pivotpal/__init__.py
pivotpal/pivotpal.py
PivotPal-0.0.6.dist-info/METADATA
PivotPal-0.0.6.dist-info/WHEEL
PivotPal-0.0.6.dist-info/top_level.txt
PivotPal-0.0.6.dist-info/RECORD
