Metadata-Version: 2.1
Name: PivotPal
Version: 0.0.6
Summary: A collection of utility functions for data analysis with pandas.
Home-page: https://github.com/ktgcreative/pivotpal
Author: Kyle Grattan
Author-email: ktgcreative@gmail.com
License: UNKNOWN
Platform: UNKNOWN
Classifier: Development Status :: 1 - Planning
Classifier: Intended Audience :: Science/Research
Classifier: Programming Language :: Python :: 3
Requires-Dist: pandas
Requires-Dist: IPython
